setup.cfg
setup.py
means/__init__.py
means.egg-info/PKG-INFO
means.egg-info/SOURCES.txt
means.egg-info/dependency_links.txt
means.egg-info/requires.txt
means.egg-info/top_level.txt
means/approximation/__init__.py
means/approximation/approximation_baseclass.py
means/approximation/lna/__init__.py
means/approximation/lna/lna.py
means/approximation/mea/__init__.py
means/approximation/mea/closure_gamma.py
means/approximation/mea/closure_log_normal.py
means/approximation/mea/closure_normal.py
means/approximation/mea/closure_scalar.py
means/approximation/mea/dmu_over_dt.py
means/approximation/mea/eq_central_moments.py
means/approximation/mea/eq_mixed_moments.py
means/approximation/mea/mea_helpers.py
means/approximation/mea/moment_expansion_approximation.py
means/approximation/mea/raw_to_central.py
means/core/__init__.py
means/core/descriptors.py
means/core/model.py
means/core/problems.py
means/examples/__init__.py
means/examples/sample_models.py
means/inference/__init__.py
means/inference/distances.py
means/inference/hypercube.py
means/inference/inference.py
means/inference/parallelisation.py
means/inference/plotting.py
means/inference/results.py
means/io/__init__.py
means/io/latex.py
means/io/sbml.py
means/io/serialise.py
means/simulation/__init__.py
means/simulation/descriptors.py
means/simulation/simulate.py
means/simulation/solvers.py
means/simulation/ssa.py
means/simulation/trajectory.py
means/tests/__init__.py
means/tests/test_LNA.py
means/tests/test_closure_gamma.py
means/tests/test_closure_log_normal.py
means/tests/test_closure_normal.py
means/tests/test_dmu_over_dt.py
means/tests/test_eq_central_moments.py
means/tests/test_eq_mixed_moments.py
means/tests/test_hypercube.py
means/tests/test_inference.py
means/tests/test_io.py
means/tests/test_mea_helpers.py
means/tests/test_memoised_property.py
means/tests/test_model.py
means/tests/test_moment_expansion_approximation.py
means/tests/test_ode_problem.py
means/tests/test_raw_to_central.py
means/tests/test_simulate.py
means/tests/test_simulate_solvers.py
means/tests/test_ssa.py
means/tests/test_sympyhelpers.py
means/tests/test_trajectory.py
