Metadata-Version: 1.1
Name: means
Version: 1.0.0
Summary: Moment Expansion Approximation method implementation with simulation and inference packages
Home-page: https://github.com/theosysbio/means
Author: Sisi Fan, Quentin Geissmann, Eszter Lakatos, Saulius Lukauskas, Angelique Ale, Ann C. Babtie, Paul D.W. Kirk, Michael P.H. Stumpf
Author-email: m.stumpf@imperial.ac.uk,e.lakatos13@imperial.ac.uk
License: MIT
Keywords: moment expansion,approximation,simulation,inference
Platform: UNKNOWN
Classifier: Intended Audience :: Science/Research
Classifier: License :: OSI Approved :: MIT License
Classifier: Topic :: Scientific/Engineering
